{"composition": {"items": [{"name": "Demais Ativos", "value": 3525336.4299999997, "percentage": 60.91}, {"name": "Ações e Derivativos", "value": 1461328.1300000001, "percentage": 25.25}, {"name": "Títulos Públicos", "value": 800824.22, "percentage": 13.84}], "date": "2013-09-30"}, "detailed": {"cnpj_fundo": "00.737.556/0001-65", "dt_comptc": "2013-09-30", "vl_patrim_liq": 1380630874.88, "blocos": [{"tipo": "titulos_publicos", "nome_display": "Títulos Públicos", "total_valor": 800824.22, "total_percentual": 0.06, "ativos": [{"nome": "LETRAS FINANCEIRAS DO TESOURO - Título público federal", "valor": 409030.58, "percentual": 0.03, "dt_venc": "2014-03-07"}, {"nome": "LETRAS FINANCEIRAS DO TESOURO - Título público federal", "valor": 391793.64, "percentual": 0.03, "dt_venc": "2014-09-07"}]}, {"tipo": "acoes_derivativos", "nome_display": "Ações e Derivativos", "total_valor": 1461328.1300000001, "total_percentual": 0.11, "ativos": [{"nome": "PETR4 - PETROBRAS    PN      N2", "valor": 308246.04, "percentual": 0.02, "tipo": "acao"}, {"nome": "BBDC4 - BRADESCO     PN  EJ  N1", "valor": 242341.26, "percentual": 0.02, "tipo": "acao"}, {"nome": "ITSA4 - ITAUSA       PN      N1", "valor": 151425.0, "percentual": 0.01, "tipo": "acao"}, {"nome": "BRFS3 - BRF SA       ON      NM", "valor": 118692.0, "percentual": 0.01, "tipo": "acao"}, {"nome": "CMIG4 - CEMIG        PN      N1", "valor": 96527.08, "percentual": 0.01, "tipo": "acao"}, {"nome": "HYPE3 - HYPERA       ON      NM", "valor": 89400.0, "percentual": 0.01, "tipo": "acao"}, {"nome": "BRML3 - BR MALLS PAR ON      NM", "valor": 84420.0, "percentual": 0.01, "tipo": "acao"}, {"nome": "UGPA3 - ULTRAPAR     ON      NM", "valor": 71058.0, "percentual": 0.01, "tipo": "acao"}, {"nome": "PCAR4 - P.ACUCAR-CBD PN      N1", "valor": 70700.0, "percentual": 0.01, "tipo": "acao"}, {"nome": "ELET6 - ELETROBRAS   PNB     N1", "valor": 58632.0, "percentual": 0.0, "tipo": "acao"}, {"nome": "GFSA3 - GAFISA       ON      NM", "valor": 57996.0, "percentual": 0.0, "tipo": "acao"}, {"nome": "DTEX3 - DURATEX      ON      NM", "valor": 35613.0, "percentual": 0.0, "tipo": "acao"}, {"nome": "BRAP4 - BRADESPAR    PN      N1", "valor": 34440.0, "percentual": 0.0, "tipo": "acao"}, {"nome": "ELET3 - ELETROBRAS   ON      N1", "valor": 15893.75, "percentual": 0.0, "tipo": "acao"}, {"nome": "ELPL4 - ELETROPAULO  PN      N2", "valor": 13680.0, "percentual": 0.0, "tipo": "acao"}, {"nome": "ALLL3 - ALL AMER LAT ON  ED  NM", "valor": 12264.0, "percentual": 0.0, "tipo": "acao"}]}], "resumo": {"Títulos Públicos": 0.06, "Ações e Derivativos": 0.11}}}