{"detail": {"cnpj_fundo": "00.792.191/0001-71", "denom_social": "PRIVATE FIX DI FAC FI", "gestor": "ITAU UNIBANCO S.A.", "classe": "Referenciado", "sit": "CANCELADA", "dt_ini": "2005-04-22", "publico_alvo": null, "dt_reg": "2005-03-16", "auditor": "PRICEWATERHOUSECOOPERS AUDITORES INDEPENDENTES LTDA.", "custodiante": "ITAU UNIBANCO S.A.", "controlador": "ITAU UNIBANCO S.A.", "admin": "BANCO ITAUCARD S.A.", "taxa_adm": null, "taxa_perf": null, "benchmark": "DI de um dia", "condom": "Aberto", "fundo_exclusivo": "N", "fundo_cotas": "S"}, "metrics": {"rentabilidade_mes": {"2004": {"5": 1.06, "6": 1.12, "7": 1.1, "8": 1.13, "9": 1.08, "10": 1.1, "11": 1.11, "12": 1.37}, "2005": {"1": 1.23, "2": 1.11, "3": 1.36, "4": -100.0}}, "rentabilidade_ano": {"2004": 10.37, "2005": -100.0}, "rentabilidade_acumulada": {"2004": 10.37, "2005": -100.0}, "volatilidade_12m": 101.47, "sharpe_12m": -1.08, "consistency": {"pos_months": 11, "neg_months": 1, "best_month": 1.37, "worst_month": -100.0}}, "structure": {"cnpj_fundo": "00.792.191/0001-71", "nome_fundo": "PRIVATE FIX DI FAC FI", "tipo": "FIC", "investe_em": [{"cnpj_fundo": "00.792.191/0001-71", "cnpj_relacionado": "01.597.187/0001-15", "nome_relacionado": "SPECIAL RENDA FIXA REFERENCIADO DI - FUNDO DE INVESTIMENTO", "tipo_relacao": "INVESTE_EM", "valor": 1577200.22}, {"cnpj_fundo": "00.792.191/0001-71", "cnpj_relacionado": "01.624.316/0001-17", "nome_relacionado": "ITAÚ RENDA FIXA REFERENCIADO DI - FUNDO DE INVESTIMENTO", "tipo_relacao": "INVESTE_EM", "valor": 91056.57}], "investido_por": [], "espelho_de": null}}